lifeguard_telegram/__init__.py
lifeguard_telegram/bot.py
lifeguard_telegram/notifications.py
lifeguard_telegram/settings.py
lifeguard_telegram/bot_handlers/__init__.py
lifeguard_telegram/bot_handlers/builtin_bot_handler.py
lifeguard_telegram-1.1.2.dist-info/METADATA
lifeguard_telegram-1.1.2.dist-info/WHEEL
lifeguard_telegram-1.1.2.dist-info/top_level.txt
lifeguard_telegram-1.1.2.dist-info/RECORD
