Metadata-Version: 2.1
Name: lifeguard-telegram
Version: 1.1.2
Summary: Lifeguard integration with Telegram
Home-page: https://github.com/LifeguardSystem/lifeguard-telegram
Author: Diego Rubin
Author-email: contact@diegorubin.dev
License: GPL2
Classifier: Development Status :: 5 - Production/Stable
Classifier: Environment :: Plugins
Classifier: Intended Audience :: Developers
Classifier: Intended Audience :: Information Technology
Classifier: Programming Language :: Python
Classifier: Programming Language :: Python :: 3
Classifier: Topic :: System :: Monitoring
Requires-Dist: lifeguard
Requires-Dist: python-telegram-bot (==13.1)
Requires-Dist: telepot
